validator/__init__.py
validator/utils.py
afrivalid-1.0.0.dist-info/METADATA
afrivalid-1.0.0.dist-info/WHEEL
afrivalid-1.0.0.dist-info/top_level.txt
afrivalid-1.0.0.dist-info/RECORD
