Metadata-Version: 2.4
Name: afrivalid
Version: 1.0.0
Summary: Validation package for African Countries identifiers, URLs, etc.
Author: Faraimunashe
Classifier: Programming Language :: Python :: 3
Classifier: License :: OSI Approved :: MIT License
Classifier: Operating System :: OS Independent
Requires-Python: >=3.6
Dynamic: author
Dynamic: classifier
Dynamic: requires-python
Dynamic: summary
